CHANGES.txt
LICENSE.txt
MANIFEST.in
README.txt
setup.py
js/__init__.py
js.bootstrap_datepicker.egg-info/PKG-INFO
js.bootstrap_datepicker.egg-info/SOURCES.txt
js.bootstrap_datepicker.egg-info/dependency_links.txt
js.bootstrap_datepicker.egg-info/entry_points.txt
js.bootstrap_datepicker.egg-info/namespace_packages.txt
js.bootstrap_datepicker.egg-info/not-zip-safe
js.bootstrap_datepicker.egg-info/requires.txt
js.bootstrap_datepicker.egg-info/top_level.txt
js/bootstrap_datepicker/__init__.py
js/bootstrap_datepicker/test_bootstrap-datepicker.txt
js/bootstrap_datepicker/resources/.DS_Store
js/bootstrap_datepicker/resources/css/datepicker.css
js/bootstrap_datepicker/resources/css/datepicker.min.css
js/bootstrap_datepicker/resources/js/bootstrap-datepicker.js
js/bootstrap_datepicker/resources/js/bootstrap-datepicker.min.js
js/bootstrap_datepicker/resources/less/.DS_Store
js/bootstrap_datepicker/resources/less/datepicker.less