Metadata-Version: 1.0
Name: js.bootstrap-datepicker
Version: 2013.03.12-1
Summary: Fanstatic packaging of Datepicker for Bootstrap (bootstrap-datepicker.js)
Home-page: https://bitbucket.org/s_nikolai/js.bootstrap_datepicker
Author: Nikolai Sevostjanov
Author-email: nikolai.sevostjanov@gmail.com
License: BSD
Platform: UNKNOWN
